CHANGES.txt
LICENSE.txt
MANIFEST.in
README.md
README.rst
setup.py
gister/__init__.py
gister/gister.py
gister.egg-info/PKG-INFO
gister.egg-info/SOURCES.txt
gister.egg-info/dependency_links.txt
gister.egg-info/entry_points.txt
gister.egg-info/requires.txt
gister.egg-info/top_level.txt