Metadata-Version: 1.1
Name: gister
Version: 1.0.22
Summary: gist making script
Home-page: https://github.com/tr3buchet/gister
Author: Trey Morris
Author-email: trey@treymorris.com
License: Apache Software License
Keywords: github,gist,gists
Platform: UNKNOWN
Classifier: Development Status :: 5 - Production/Stable
Classifier: License :: OSI Approved :: Apache Software License
